MANIFEST.in
setup.cfg
setup.py
examples/full_score.vcf
examples/my_test.vcf
examples/trio_ped.txt
score_mip_variants/__init__.py
score_mip_variants/plugin_rank_model_cmms.py
score_mip_variants/plugin_reader.py
score_mip_variants/score_model.py
score_mip_variants/variant_scorer.py
score_mip_variants/variant_sorter.py
score_mip_variants.egg-info/PKG-INFO
score_mip_variants.egg-info/SOURCES.txt
score_mip_variants.egg-info/dependency_links.txt
score_mip_variants.egg-info/requires.txt
score_mip_variants.egg-info/top_level.txt
score_mip_variants/configs/__init__.py
score_mip_variants/configs/rank_model_cmms_v1.0.ini
scripts/score_mip_variants