Metadata-Version: 1.1
Name: score-mip-variants
Version: 0.6.2
Summary: Annotate vcf variants with a rank score
Home-page: http://github.com/moonso/rank_mip_variants
Author: Mans Magnusson
Author-email: mans.magnusson@scilifelab.se
License: MIT License
Keywords: ranking,scoring,vcf,variants
Platform: UNKNOWN
Classifier: Programming Language :: Python
Classifier: Programming Language :: Python :: 2.7
Classifier: Programming Language :: Python :: 3
Classifier: License :: OSI Approved :: MIT License
Classifier: Development Status :: 4 - Beta
Classifier: Operating System :: MacOS :: MacOS X
Classifier: Operating System :: Unix
Classifier: Intended Audience :: Science/Research
Classifier: Topic :: Scientific/Engineering :: Bio-Informatics
